{
  "db_name": "PostgreSQL",
  "query": "INSERT INTO transactions (user_id, status, niche, rank, amount) VALUES ($1, 'pending', $2, $3, $4) RETURNING id",
  "describe": {
    "columns": [
      {
        "ordinal": 0,
        "name": "id",
        "type_info": "Uuid"
      }
    ],
    "parameters": {
      "Left": [
        "Uuid",
        "Text",
        "Text",
        "Int4"
      ]
    },
    "nullable": [
      false
    ]
  },
  "hash": "33c74c1e21b35e21c2ff3bd0ca50e7d26b8f040d82d6bfd89d6d1960df74c55e"
}
